rhasspyclient/__init__.py
rhasspyclient/__main__.py
rhasspyclient/intent.py
rhasspyclient/speech.py
rhasspyclient/train.py
rhasspyclient/utils.py
rhasspy_client-1.1.1.dist-info/LICENSE
rhasspy_client-1.1.1.dist-info/METADATA
rhasspy_client-1.1.1.dist-info/WHEEL
rhasspy_client-1.1.1.dist-info/top_level.txt
rhasspy_client-1.1.1.dist-info/RECORD
