Metadata-Version: 2.1
Name: rhasspy-client
Version: 1.1.1
Summary: Client library for talking to remote Rhasspy server
Home-page: https://github.com/rhasspy/rhasspy-client
Author: Michael Hansen
Author-email: hansen.mike@gmail.com
License: UNKNOWN
Platform: UNKNOWN
Classifier: Programming Language :: Python :: 3
Classifier: Programming Language :: Python :: 3.6
Classifier: Programming Language :: Python :: 3.7
Classifier: Programming Language :: Python :: 3.8
Classifier: License :: OSI Approved :: MIT License
Requires-Python: >=3.6
Requires-Dist: aiohttp (==3.6.2)
Requires-Dist: attrs (==19.3.0)
Requires-Dist: jsonlines (==1.2.0)
